Metadata-Version: 2.1
Name: COWBAT
Version: 0.5.0.21
Summary: CFIA OLC Workflow for Bacterial Assembly and Typing
Home-page: https://github.com/OLC-Bioinformatics/COWBAT
Author: Adam Koziol
Author-email: adam.koziol@inspection.gc.ca
License: MIT
Platform: UNKNOWN
License-File: LICENSE
